odoo/addons/fieldservice_isp_flow/README.rst
odoo/addons/fieldservice_isp_flow/__init__.py
odoo/addons/fieldservice_isp_flow/__manifest__.py
odoo/addons/fieldservice_isp_flow/data/fsm_stage.xml
odoo/addons/fieldservice_isp_flow/i18n/de.po
odoo/addons/fieldservice_isp_flow/i18n/es.po
odoo/addons/fieldservice_isp_flow/i18n/es_AR.po
odoo/addons/fieldservice_isp_flow/i18n/es_CL.po
odoo/addons/fieldservice_isp_flow/i18n/fieldservice_isp_flow.pot
odoo/addons/fieldservice_isp_flow/i18n/it.po
odoo/addons/fieldservice_isp_flow/i18n/pt_BR.po
odoo/addons/fieldservice_isp_flow/models/__init__.py
odoo/addons/fieldservice_isp_flow/models/fsm_order.py
odoo/addons/fieldservice_isp_flow/readme/CONFIGURE.md
odoo/addons/fieldservice_isp_flow/readme/CONTRIBUTORS.md
odoo/addons/fieldservice_isp_flow/readme/CREDITS.md
odoo/addons/fieldservice_isp_flow/readme/DESCRIPTION.md
odoo/addons/fieldservice_isp_flow/readme/ROADMAP.md
odoo/addons/fieldservice_isp_flow/readme/USAGE.md
odoo/addons/fieldservice_isp_flow/static/description/icon.png
odoo/addons/fieldservice_isp_flow/static/description/index.html
odoo/addons/fieldservice_isp_flow/tests/__init__.py
odoo/addons/fieldservice_isp_flow/tests/test_fsm_isp_flow.py
odoo/addons/fieldservice_isp_flow/views/fsm_order.xml
odoo_addon_fieldservice_isp_flow-17.0.1.0.0.6.dist-info/METADATA
odoo_addon_fieldservice_isp_flow-17.0.1.0.0.6.dist-info/WHEEL
odoo_addon_fieldservice_isp_flow-17.0.1.0.0.6.dist-info/top_level.txt
odoo_addon_fieldservice_isp_flow-17.0.1.0.0.6.dist-info/RECORD
